Workbook

Sheet 📋 Leia-me
A1: 📋 CONTROLE DE CAMPANHAS — AFILIADO GOOGLE ADS
A3: 🎯 CONVENÇÃO DE CORES
A4: 🔵 Azul (fundo #dce6f7) → Células para VOCÊ preencher (dados diários, datas, configurações)
A5: ⬜ Cinza (fundo #f0f0f0) → Fórmulas automáticas — NÃO editar
A6: 🟡 Amarelo (fundo #fff2cc) → Metas ajustáveis (ROAS alvo, comissão, amostra mínima)
A7: 🟢 Verde → Performance boa / Aprovado / OK
A8: 🔴 Vermelho → Atenção / Ação necessária / Estouro de caracteres
A10: 📑 ORDEM DE USO DAS ABAS
A11: 1. 📋 Leia-me → Leia estas instruções antes de tudo
A12: 2. 🎯 Produto & Oferta → Verifique os dados do produto (já preenchidos)
A13: 3. 🌐 Assets & Domínio → Complete itens pendentes (⏳) antes de ativar
A14: 4. ⚙️ Config Campanha → Revise configurações, marque checklist, ative campanha
... A61: • Meta: ROAS ≥ 2.0 sustentável

Sheet 🎯 Produto & Oferta
A1: 🎯 DADOS DO PRODUTO & OFERTA
A3: Campo | B3: Valor | C3: Observação
A4: Plataforma | B4: ClickBank
A5: Nick Afiliado | B5: genautech
A6: Vendor | B6: citrusburn
A7: Nome do Produto | B7: CitrusBurn
A8: HopLink Completo | B8: https://hop.clickbank.net/?affiliate=genautech&vendor=citrusburn&tid=gads&pid=shop | C8: Copiar este link na bridge page
A9: Tracking ID | B9: gads | C9: Identifica tráfego do Google Ads
A10: Landing Page Type | B10: Shopify Style (pid=shop) | C10: Melhor para cold traffic
A11: Comissão % | B11: 85% | C11: Máxima comissão disponível
A13: TABELA DE PREÇOS E COMISSÕES
A14: Produto 1 (2 frascos) | B14: $158.00 | C14: Comissão: $134.00
A15: Produto 2 (3 frascos) | B15: $207.00 | C15: Comissão: $176.00
A16: Produto 3 (6 frascos) | B16: $294.00 | C16: Comissão: $250.00
A17: Comissão Média Conservadora | B17: $134.00 | C17: Usada para cálculos (pedido menor)
A19: INFORMAÇÕES DO PRODUTO
A20: Garantia | B20: 180 dias money-back | C20: Argumento forte para copy
A21: Mercado Alvo | B21: United States
A22: Público-Alvo | B22: Mulheres 40-65+ anos | C22: Foco em menopausa e metabolismo
A23: Claim Principal | B23: Seville Orange Peel melts belly fat / Thermogenic Resistance | C23: Não usar claims médicos absolutos!
A25: INTEGRAÇÃO GOOGLE ADS
A26: Status da Integração | B26: ✅ ACTIVE | C26: ClickBank ↔ Google Ads
A27: Conta Google Ads | B27: genaujunior@gmail.com
A28: Conversão 1 | B28: ClickBank Initial Purchase | C28: Venda principal
A29: Conversão 2 | B29: ClickBank Upsell Purchase | C29: Upsells
A30: Conversão 3 | B30: ClickBank Order Form Impression | C30: Visualização do checkout
A32: REGRAS DO PRODUTOR (PROIBIÇÕES)
A33: ❌ Link direto | B33: Proibido — usar bridge page | C33: Obrigatório intermediar
A34: ❌ Palavra 'scam' | B34: Proibido em anúncios e páginas
A35: ❌ Claims médicos absolutos | B35: Proibido ('cura', 'trata', 'garante') | C35: Usar 'supports', 'may help'
A36: ❌ Deepfakes | B36: Proibido usar IA para simular pessoas

Sheet 🌐 Assets & Domínio
A1: 🌐 ASSETS & DOMÍNIO DA CAMPANHA
A3: Asset | B3: Valor / URL | C3: Status | D3: Ação Necessária
A4: DOMÍNIO & PÁGINAS
A5: Domínio Principal | B5: getlymphflow.shop | C5: ✅ Ativo
A6: URL Bridge Page | B6: getlymphflow.shop/citruspburn | C6: ⏳ Publicar | D6: Subir HTML para WordPress
A7: Arquivo HTML Bridge | B7: /home/ubuntu/citruspburn-bridge.html | C7: ✅ Criado | D7: Fazer upload ao WordPress
A8: Headline da Bridge | B8: Spanish Scientists Discover New Way to Melt Stubborn Belly Fat | C8: ✅ Definido
A9: CTA da Bridge | B9: Watch the Free Video Now → | C9: ✅ Definido
A10: Página /privacy-policy | B10: getlymphflow.shop/privacy-policy | C10: ⏳ Fazer | D10: Criar com plugin WP
A11: Página /terms | B11: getlymphflow.shop/terms | C11: ⏳ Fazer | D11: Criar com plugin WP
A12: Página /disclaimer | B12: getlymphflow.shop/disclaimer | C12: ⏳ Fazer | D12: Incluir disclaimer de afiliado
A13: Página /contact | B13: getlymphflow.shop/contact | C13: ⏳ Fazer | D13: Formulário ou e-mail
A14: Imagem do Produto | B14: Baixar em citrusburn.com/affiliates | C14: ⏳ Baixar | D14: Usar na bridge page
A16: GOOGLE ADS — TRACKING
A17: Google Ads Account ID | B17: AW-XXXXXXXXXX | C17: ⏳ Preencher | D17: Pegar no Google Ads → canto superior
A18: Conversion Label | B18: (ver no Google Ads) | C18: ⏳ Preencher | D18: Configurações → Conversões
A19: Auto-tagging | B19: — | C19: ⏳ Verificar | D19: Google Ads → Settings → Auto-tagging ON
A21: CAMPAIGN URL SUFFIX
A22: URL Suffix Completo | B22: utm_source=google&utm_medium=cpc&utm_campaign={campaignid}&utm_term={keyword}&utm_content={adgroupid}&traffic_source=google | C22: ✅ Definido | D22: Aplicar na campanha
A23: utm_source | B23: google | C23: ✅
A24: utm_medium | B24: cpc | C24: ✅
A25: utm_campaign | B25: {campaignid} | C25: ✅ | D25: Dinâmico
A26: utm_term | B26: {keyword} | C26: ✅ | D26: Rastreia keyword
A27: utm_content | B27: {adgroupid} | C27: ✅ | D27: Rastreia ad group
A28: traffic_source | B28: google | C28: ✅ | D28: Para ClickBank

Sheet ⚙️ Config Campanha
A1: ⚙️ CONFIGURAÇÕES DA CAMPANHA GOOGLE ADS
A3: Configuração | B3: Valor | C3: Verificação
A4: CONFIGURAÇÕES GERAIS
A5: Nome da Campanha | B5: PESQ-METABOLISMO-VENDAS-FASE1 | C5: ✅
A6: Tipo de Campanha | B6: Search | C6: ✅
A7: Objetivo | B7: Sales / Conversions | C7: ✅
A8: Fase Atual | B8: Fase 1 — Validação | C8: ✅
A9: Localização | B9: United States | C9: ✅
A10: Idioma | B10: English | C10: ✅
A11: Rede de Display | B11: DESATIVADA | C11: ✅ Obrigatório desativar
A12: Parceiros de Pesquisa | B12: DESATIVADO | C12: ✅ Obrigatório desativar
A13: Config de Local | B13: Presença: "pessoas EM ou regularmente em" | C13: ✅ Não usar 'interesse'
A15: BUDGET & LANCES
A16: Budget Diário Fase 1 | B16: $2.00/dia | C16: ✅
A17: Budget Total Fase 1 | B17: $10.00 | C17: 5 dias × $2
A18: Tipo de Lance | B18: CPC Manual | C18: ✅ Sem Enhanced CPC
A19: Lance Máximo CPC | B19: $0.80 | C19: Não ultrapassar na fase 1
A21: URLS & TRACKING
A22: URL Final | B22: https://getlymphflow.shop/citruspburn | C22: ⏳ Publicar bridge primeiro
A23: Campaign URL Suffix | B23: utm_source=google&utm_medium=cpc&utm_campaign={campaignid}&utm_term={keyword}&utm_content={adgroupid}&traffic_source=google | C23: ✅
A25: DATAS
A26: Data de Início | C26: ← Preencher quando ativar
A27: Data Início Fase 2 | C27: ← Calcular: início + 5 dias
A28: Status da Campanha | B28: Pausada | C28: ⚠️ Rever checklist antes de ativar
A31: ✅ CHECKLIST PRÉ-ATIVAÇÃO
A32: ☐ | B32: Bridge page publicada e funcionando (testar no celular) | C32: ⏳ Verificar
A33: ☐ | B33: HopLink na bridge redireciona para página de vendas | C33: ⏳ Verificar
A34: ☐ | B34: Páginas legais criadas (/privacy, /terms, /disclaimer, /contact) | C34: ⏳ Verificar
A35: ☐ | B35: Auto-tagging ativado no Google Ads | C35: ⏳ Verificar
A36: ☐ | B36: Conversões ClickBank aparecendo no Google Ads | C36: ⏳ Verificar
A37: ☐ | B37: URL Suffix configurado na campanha | C37: ⏳ Verificar

Sheet 🔑 Palavras-chave
A1: 🔑 PALAVRAS-CHAVE DA CAMPANHA
A3: GRUPO 1 — PROBLEMA (Awareness)
A4: Keyword | B4: Tipo de Match | C4: Intenção | D4: CPC Estimado | E4: Status | F4: Observação
A5: [slow metabolism after 40] | B5: Exact | C5: Problema / Dor | D5: $0.60 | E5: Ativa
A6: [thermogenic resistance] | B6: Exact | C6: Problema científico | D6: $0.50 | E6: Ativa
A7: [why cant i lose weight after 40] | B7: Exact | C7: Problema / Dor | D7: $0.70 | E7: Ativa
A8: [metabolism fix women over 40] | B8: Exact | C8: Problema + Solução | D8: $0.65 | E8: Ativa
A9: [belly fat menopause solution] | B9: Exact | C9: Problema + Solução | D9: $0.80 | E9: Ativa
A11: GRUPO 2 — SOLUÇÃO (Intent)
A12: Keyword | B12: Tipo de Match | C12: Intenção | D12: CPC Estimado | E12: Status | F12: Observação
A13: [seville orange weight loss supplement] | B13: Exact | C13: Solução específica | D13: $0.55 | E13: Ativa
A14: [citrus burn metabolism] | B14: Exact | C14: Branded / Produto | D14: $0.50 | E14: Ativa
A15: [natural thermogenic for women] | B15: Exact | C15: Solução genérica | D15: $0.70 | E15: Ativa
A16: [best metabolism booster over 40] | B16: Exact | C16: Solução comparativa | D16: $0.75 | E16: Ativa
A17: [spanish orange peel fat burn] | B17: Exact | C17: Solução específica | D17: $0.60 | E17: Ativa
A19: RESUMO
A20: Keywords Ativas Grupo 1: | B20: =COUNTIF(E5:E9,"Ativa") -> 5
A21: Keywords Ativas Grupo 2: | B21: =COUNTIF(E13:E17,"Ativa") -> 5
A22: Total Keywords Ativas: | B22: =B20+B21 -> 10
A24: ⚠️ REGRA DE CORRESPONDÊNCIA — FASE 1
A25: Usar APENAS [exact] e "phrase" match na fase 1. NUNCA usar broad match com budget limitado.

Sheet 🚫 Negativas
A1: 🚫 PALAVRAS-CHAVE NEGATIVAS
A3: Palavra Negativa | B3: Tipo | C3: Fonte | D3: Data de Adição | E3: Motivo
A4: free | B4: Exact | C4: Pré-definido | D4: Pré-campanha | E4: Sem intenção de compra
A5: youtube | B5: Exact | C5: Pré-definido | D5: Pré-campanha | E5: Busca por vídeo, não compra
A6: reddit | B6: Exact | C6: Pré-definido | D6: Pré-campanha | E6: Busca por review/forum
A7: amazon | B7: Exact | C7: Pré-definido | D7: Pré-campanha | E7: Busca em marketplace
A8: walmart | B8: Exact | C8: Pré-definido | D8: Pré-campanha | E8: Busca em marketplace
A9: scam | B9: Exact | C9: Pré-definido | D9: Pré-campanha | E9: Tráfego negativo + proibido pelo vendor
A10: side effects | B10: Phrase | C10: Pré-definido | D10: Pré-campanha | E10: Intenção de pesquisa, não compra
A11: lawsuit | B11: Exact | C11: Pré-definido | D11: Pré-campanha | E11: Tráfego negativo
A12: wikipedia | B12: Exact | C12: Pré-definido | D12: Pré-campanha | E12: Busca informacional
A13: how to make | B13: Phrase | C13: Pré-definido | D13: Pré-campanha | E13: DIY, sem intenção de compra
A35: 💡 INSTRUÇÕES
A36: • Adicione negativas do Search Terms Report semanalmente (segunda-feira)
A37: • No Google Ads, crie uma Lista de Negativas compartilhada para reaproveitar entre campanhas
A38: • Priorize adicionar termos com cliques mas 0 conversões

Sheet ✍️ Copy RSA
A1: ✍️ COPY DOS ANÚNCIOS (RSA — Responsive Search Ads)
A3: SEÇÃO 1 — HEADLINES (máx. 30 caracteres cada)
A4: # | B4: Headline | C4: Caracteres | D4: Limite | E4: Status | F4: Ângulo | G4: Fixar?
A5: 1 | B5: Spanish Orange Peel Burns Belly Fat | C5: =LEN(B5) -> 35 | D5: 30 | E5: =IF(C5<=30,"✅ OK","❌ ESTOURO") -> ❌ ESTOURO | F5: Curiosidade / Ingrediente | G5: —
A6: 2 | B6: The Real Cause of Slow Metabolism at 40 | C6: =LEN(B6) -> 39 | D6: 30 | E6: =IF(C6<=30,"✅ OK","❌ ESTOURO") -> ❌ ESTOURO | F6: Problema / Dor | G6: —
A7: 3 | B7: Thermogenic Resistance Fix — Watch Now | C7: =LEN(B7) -> 38 | D7: 30 | E7: =IF(C7<=30,"✅ OK","❌ ESTOURO") -> ❌ ESTOURO | F7: Científico / CTA | G7: —
A8: 4 | B8: Natural Metabolism Booster for Women | C8: =LEN(B8) -> 36 | D8: 30 | E8: =IF(C8<=30,"✅ OK","❌ ESTOURO") -> ❌ ESTOURO | F8: Solução / Gênero | G8: —
A9: 5 | B9: Seville Orange Melts Fat While You Sleep | C9: =LEN(B9) -> 40 | D9: 30 | E9: =IF(C9<=30,"✅ OK","❌ ESTOURO") -> ❌ ESTOURO | F9: Benefício / Ingrediente | G9: —
A10: 6 | B10: Going Viral: This Morning Ritual Works | C10: =LEN(B10) -> 38 | D10: 30 | E10: =IF(C10<=30,"✅ OK","❌ ESTOURO") -> ❌ ESTOURO | F10: Social Proof / Curiosidade | G10: —
A11: 7 | B11: CitrusBurn Official — Limited Stock | C11: =LEN(B11) -> 35 | D11: 30 | E11: =IF(C11<=30,"✅ OK","❌ ESTOURO") -> ❌ ESTOURO | F11: Branded / Urgência | G11: —
A12: 8 | B12: 74% More Thermogenesis Naturally | C12: =LEN(B12) -> 32 | D12: 30 | E12: =IF(C12<=30,"✅ OK","❌ ESTOURO") -> ❌ ESTOURO | F12: Estatística / Científico | G12: —
A13: 9 | B13: Over 40 and Can't Lose Weight? Try This | C13: =LEN(B13) -> 39 | D13: 30 | E13: =IF(C13<=30,"✅ OK","❌ ESTOURO") -> ❌ ESTOURO | F13: Problema / CTA | G13: —
A14: 10 | B14: 180-Day Guarantee — Risk Free | C14: =LEN(B14) -> 29 | D14: 30 | E14: =IF(C14<=30,"✅ OK","❌ ESTOURO") -> ✅ OK | F14: Garantia / Confiança | G14: —
A15: 11 | B15: Made in FDA-Registered USA Facility | C15: =LEN(B15) -> 35 | D15: 30 | E15: =IF(C15<=30,"✅ OK","❌ ESTOURO") -> ❌ ESTOURO | F15: Confiança / Qualidade | G15: —
A16: 12 | B16: No Stimulants No Jitters No Prescription | C16: =LEN(B16) -> 40 | D16: 30 | E16: =IF(C16<=30,"✅ OK","❌ ESTOURO") -> ❌ ESTOURO | F16: Objeção / Segurança | G16: —
... A19: 15 | B19: Watch the Free Video Today | C19: =LEN(B19) -> 26 | D19: 30 | E19: =IF(C19<=30,"✅ OK","❌ ESTOURO") -> ✅ OK | F19: CTA Direto | G19: —
A22: SEÇÃO 2 — DESCRIPTIONS (máx. 90 caracteres cada)
A23: # | B23: Description | C23: Caracteres | D23: Limite | E23: Status
A24: 1 | B24: Thermogenic resistance blocks fat loss after 40. Seville Orange targets the root cause naturally. 180-day money-back guarantee. Watch the free video. | C24: =LEN(B24) -> 149 | D24: 90 | E24: =IF(C24<=90,"✅ OK","❌ ESTOURO") -> ❌ ESTOURO
A25: 2 | B25: Spanish scientists discovered why diets fail over 40. 100% natural ingredients. FDA-registered facility. No prescription needed. Watch the free video now. | C25: =LEN(B25) -> 154 | D25: 90 | E25: =IF(C25<=90,"✅ OK","❌ ESTOURO") -> ❌ ESTOURO
A26: 3 | B26: CitrusBurn uses Seville Orange & Berberine to reset your metabolism. Stimulant-free formula. Results in 60 days or full refund. See the free video today. | C26: =LEN(B26) -> 153 | D26: 90 | E26: =IF(C26<=90,"✅ OK","❌ ESTOURO") -> ❌ ESTOURO
A29: SEÇÃO 3 — DISPLAY PATHS
A30: Path 1: | B30: Metabolism | C30: URL exibida: getlymphflow.shop/Metabolism/Official
A31: Path 2: | B31: Official
A34: ⚠️ CHECKLIST DE COMPLIANCE
A35: ✅ Não contém "cure" / "cura" / "treat" / "trata"
A36: ✅ Não contém "guarantee weight loss" (claim absoluto)
A37: ✅ Não contém "scam"
A38: ✅ Não contém claims médicos diretos
A39: ✅ Usa linguagem condicional ("may help", "supports", "targets")
A40: ✅ Inclui "Watch the free video" como CTA (não venda direta)

Sheet 📊 Controle Diário
A1: 📊 CONTROLE DIÁRIO DE PERFORMANCE
A2: Preencha as células AZUIS diariamente com dados do Google Ads. As fórmulas calculam o resto automaticamente.
A3: AZUL | B3: Fórmula | C3: AZUL | D3: AZUL | E3: AZUL | F3: AZUL | G3: AZUL | H3: Fórmula | I3: Fórmula | J3: Fórmula | K3: Fórmula | L3: Fórmula | M3: Fórmula | N3: Fórmula | O3: AZUL
A4: Data | B4: Dia da Semana | C4: Fase | D4: Impressões | E4: Cliques | F4: Gasto (USD) | G4: Conversões | H4: CTR | I4: CPC Médio | J4: CPA | K4: Receita | L4: ROAS | M4: Lucro | N4: Status do Dia | O4: Observações
B5: =IF(A5="","",TEXT(A5,"dddd")) | H5: =IF(D5=0,0,E5/D5) -> 0 | I5: =IF(E5=0,0,F5/E5) -> 0 | J5: =IF(G5=0,"—",F5/G5) -> — | K5: =G5*134 -> 0 | L5: =IF(F5=0,"—",K5/F5) -> — | M5: =K5-F5 -> 0 | N5: =IF(A5="","",IF(G5>0,IF(F5/IF(G5=0,1,G5)>134,"⚠️ Verificar","✅ Converteu!"),"📊 Coletando dados")) | O5: ← Exemplo: preencha assim
B6: =IF(A6="","",TEXT(A6,"dddd")) | H6: =IF(D6=0,0,E6/D6) -> 0 | I6: =IF(E6=0,0,F6/E6) -> 0 | J6: =IF(G6=0,"—",F6/G6) -> — | K6: =G6*134 -> 0 | L6: =IF(F6=0,"—",K6/F6) -> — | M6: =K6-F6 -> 0 | N6: =IF(A6="","",IF(G6>0,IF(F6/IF(G6=0,1,G6)>134,"⚠️ Verificar","✅ Converteu!"),"📊 Coletando dados"))
B7: =IF(A7="","",TEXT(A7,"dddd")) | H7: =IF(D7=0,0,E7/D7) -> 0 | I7: =IF(E7=0,0,F7/E7) -> 0 | J7: =IF(G7=0,"—",F7/G7) -> — | K7: =G7*134 -> 0 | L7: =IF(F7=0,"—",K7/F7) -> — | M7: =K7-F7 -> 0 | N7: =IF(A7="","",IF(G7>0,IF(F7/IF(G7=0,1,G7)>134,"⚠️ Verificar","✅ Converteu!"),"📊 Coletando dados"))
B8: =IF(A8="","",TEXT(A8,"dddd")) | H8: =IF(D8=0,0,E8/D8) -> 0 | I8: =IF(E8=0,0,F8/E8) -> 0 | J8: =IF(G8=0,"—",F8/G8) -> — | K8: =G8*134 -> 0 | L8: =IF(F8=0,"—",K8/F8) -> — | M8: =K8-F8 -> 0 | N8: =IF(A8="","",IF(G8>0,IF(F8/IF(G8=0,1,G8)>134,"⚠️ Verificar","✅ Converteu!"),"📊 Coletando dados"))
B9: =IF(A9="","",TEXT(A9,"dddd")) | H9: =IF(D9=0,0,E9/D9) -> 0 | I9: =IF(E9=0,0,F9/E9) -> 0 | J9: =IF(G9=0,"—",F9/G9) -> — | K9: =G9*134 -> 0 | L9: =IF(F9=0,"—",K9/F9) -> — | M9: =K9-F9 -> 0 | N9: =IF(A9="","",IF(G9>0,IF(F9/IF(G9=0,1,G9)>134,"⚠️ Verificar","✅ Converteu!"),"📊 Coletando dados"))
B10: =IF(A10="","",TEXT(A10,"dddd")) | H10: =IF(D10=0,0,E10/D10) -> 0 | I10: =IF(E10=0,0,F10/E10) -> 0 | J10: =IF(G10=0,"—",F10/G10) -> — | K10: =G10*134 -> 0 | L10: =IF(F10=0,"—",K10/F10) -> — | M10: =K10-F10 -> 0 | N10: =IF(A10="","",IF(G10>0,IF(F10/IF(G10=0,1,G10)>134,"⚠️ Verificar","✅ Converteu!"),"📊 Coletando dados"))
B11: =IF(A11="","",TEXT(A11,"dddd")) | H11: =IF(D11=0,0,E11/D11) -> 0 | I11: =IF(E11=0,0,F11/E11) -> 0 | J11: =IF(G11=0,"—",F11/G11) -> — | K11: =G11*134 -> 0 | L11: =IF(F11=0,"—",K11/F11) -> — | M11: =K11-F11 -> 0 | N11: =IF(A11="","",IF(G11>0,IF(F11/IF(G11=0,1,G11)>134,"⚠️ Verificar","✅ Converteu!"),"📊 Coletando dados"))
B12: =IF(A12="","",TEXT(A12,"dddd")) | H12: =IF(D12=0,0,E12/D12) -> 0 | I12: =IF(E12=0,0,F12/E12) -> 0 | J12: =IF(G12=0,"—",F12/G12) -> — | K12: =G12*134 -> 0 | L12: =IF(F12=0,"—",K12/F12) -> — | M12: =K12-F12 -> 0 | N12: =IF(A12="","",IF(G12>0,IF(F12/IF(G12=0,1,G12)>134,"⚠️ Verificar","✅ Converteu!"),"📊 Coletando dados"))
B13: =IF(A13="","",TEXT(A13,"dddd")) | H13: =IF(D13=0,0,E13/D13) -> 0 | I13: =IF(E13=0,0,F13/E13) -> 0 | J13: =IF(G13=0,"—",F13/G13) -> — | K13: =G13*134 -> 0 | L13: =IF(F13=0,"—",K13/F13) -> — | M13: =K13-F13 -> 0 | N13: =IF(A13="","",IF(G13>0,IF(F13/IF(G13=0,1,G13)>134,"⚠️ Verificar","✅ Converteu!"),"📊 Coletando dados"))
B14: =IF(A14="","",TEXT(A14,"dddd")) | H14: =IF(D14=0,0,E14/D14) -> 0 | I14: =IF(E14=0,0,F14/E14) -> 0 | J14: =IF(G14=0,"—",F14/G14) -> — | K14: =G14*134 -> 0 | L14: =IF(F14=0,"—",K14/F14) -> — | M14: =K14-F14 -> 0 | N14: =IF(A14="","",IF(G14>0,IF(F14/IF(G14=0,1,G14)>134,"⚠️ Verificar","✅ Converteu!"),"📊 Coletando dados"))
B15: =IF(A15="","",TEXT(A15,"dddd")) | H15: =IF(D15=0,0,E15/D15) -> 0 | I15: =IF(E15=0,0,F15/E15) -> 0 | J15: =IF(G15=0,"—",F15/G15) -> — | K15: =G15*134 -> 0 | L15: =IF(F15=0,"—",K15/F15) -> — | M15: =K15-F15 -> 0 | N15: =IF(A15="","",IF(G15>0,IF(F15/IF(G15=0,1,G15)>134,"⚠️ Verificar","✅ Converteu!"),"📊 Coletando dados"))
B16: =IF(A16="","",TEXT(A16,"dddd")) | H16: =IF(D16=0,0,E16/D16) -> 0 | I16: =IF(E16=0,0,F16/E16) -> 0 | J16: =IF(G16=0,"—",F16/G16) -> — | K16: =G16*134 -> 0 | L16: =IF(F16=0,"—",K16/F16) -> — | M16: =K16-F16 -> 0 | N16: =IF(A16="","",IF(G16>0,IF(F16/IF(G16=0,1,G16)>134,"⚠️ Verificar","✅ Converteu!"),"📊 Coletando dados"))
B17: =IF(A17="","",TEXT(A17,"dddd")) | H17: =IF(D17=0,0,E17/D17) -> 0 | I17: =IF(E17=0,0,F17/E17) -> 0 | J17: =IF(G17=0,"—",F17/G17) -> — | K17: =G17*134 -> 0 | L17: =IF(F17=0,"—",K17/F17) -> — | M17: =K17-F17 -> 0 | N17: =IF(A17="","",IF(G17>0,IF(F17/IF(G17=0,1,G17)>134,"⚠️ Verificar","✅ Converteu!"),"📊 Coletando dados"))
... B35: =IF(A35="","",TEXT(A35,"dddd")) | H35: =IF(D35=0,0,E35/D35) -> 0 | I35: =IF(E35=0,0,F35/E35) -> 0 | J35: =IF(G35=0,"—",F35/G35) -> — | K35: =G35*134 -> 0 | L35: =IF(F35=0,"—",K35/F35) -> — | M35: =K35-F35 -> 0 | N35: =IF(A35="","",IF(G35>0,IF(F35/IF(G35=0,1,G35)>134,"⚠️ Verificar","✅ Converteu!"),"📊 Coletando dados"))
A37: TOTAIS / MÉDIAS | C37: — | D37: =SUM(D5:D35) -> 0 | E37: =SUM(E5:E35) -> 0 | F37: =SUM(F5:F35) -> 0 | G37: =SUM(G5:G35) -> 0 | H37: =IF(D37=0,0,E37/D37) -> 0 | I37: =IF(E37=0,0,F37/E37) -> 0 | J37: =IF(G37=0,"—",F37/G37) -> — | K37: =SUM(K5:K35) -> 0 | L37: =IF(F37=0,"—",K37/F37) -> — | M37: =K37-F37 -> 0
A39: ⚠️ ALERTA REGRA 3×: | C39: =IF(AND(F37>=402,G37=0),"🚨 GASTO ≥ $402 SEM CONVERSÃO — AVALIAR TROCA DE OFERTA!","✅ Dentro do limite") -> ✅ Dentro do limite

Sheet 📈 Métricas Semanais
A1: 📈 MÉTRICAS SEMANAIS — CONSOLIDAÇÃO
A3: METAS AJUSTÁVEIS → | B3: Meta ROAS: | C3: 2 | D3: Comissão Média: | E3: 134 | F3: Regra 3×: | G3: =E3*3 -> 402 | H3: Amostra Mínima: | I3: 100
A5: Semana # | B5: De | C5: Até | D5: Impressões | E5: Cliques | F5: Gasto (USD) | G5: Conversões | H5: CTR Médio | I5: CPC Médio | J5: CPA | K5: Receita | L5: ROAS | M5: Lucro | N5: Amostra? | O5: Veredicto | P5: Ação Tomada
A6: 1 | H6: =IF(D6=0,0,E6/D6) -> 0 | I6: =IF(E6=0,0,F6/E6) -> 0 | J6: =IF(G6=0,"—",F6/G6) -> — | K6: =G6*$E$3 -> 0 | L6: =IF(F6=0,"—",K6/F6) -> — | M6: =K6-F6 -> 0 | N6: =IF(E6>=$I$3,"✅ Sim","⏳ Falta "&$I$3-E6&" cliques") -> ⏳ Falta 100 cliques | O6: =IF(E6<$I$3,"📊 COLETAR DADOS",IF(AND(L6>=$C$3,E6>=$I$3),"✔ ESCALAR",IF(AND(F6>=$G$3,G6=0),"✖ PAUSAR / TROCAR OFERTA",IF(AND(L6>=1,L6<$C$3),"⚙ OTIMIZAR","📊 COLETAR DADOS")))) -> 📊 COLETAR DADOS
A7: 2 | H7: =IF(D7=0,0,E7/D7) -> 0 | I7: =IF(E7=0,0,F7/E7) -> 0 | J7: =IF(G7=0,"—",F7/G7) -> — | K7: =G7*$E$3 -> 0 | L7: =IF(F7=0,"—",K7/F7) -> — | M7: =K7-F7 -> 0 | N7: =IF(E7>=$I$3,"✅ Sim","⏳ Falta "&$I$3-E7&" cliques") -> ⏳ Falta 100 cliques | O7: =IF(E7<$I$3,"📊 COLETAR DADOS",IF(AND(L7>=$C$3,E7>=$I$3),"✔ ESCALAR",IF(AND(F7>=$G$3,G7=0),"✖ PAUSAR / TROCAR OFERTA",IF(AND(L7>=1,L7<$C$3),"⚙ OTIMIZAR","📊 COLETAR DADOS")))) -> 📊 COLETAR DADOS
A8: 3 | H8: =IF(D8=0,0,E8/D8) -> 0 | I8: =IF(E8=0,0,F8/E8) -> 0 | J8: =IF(G8=0,"—",F8/G8) -> — | K8: =G8*$E$3 -> 0 | L8: =IF(F8=0,"—",K8/F8) -> — | M8: =K8-F8 -> 0 | N8: =IF(E8>=$I$3,"✅ Sim","⏳ Falta "&$I$3-E8&" cliques") -> ⏳ Falta 100 cliques | O8: =IF(E8<$I$3,"📊 COLETAR DADOS",IF(AND(L8>=$C$3,E8>=$I$3),"✔ ESCALAR",IF(AND(F8>=$G$3,G8=0),"✖ PAUSAR / TROCAR OFERTA",IF(AND(L8>=1,L8<$C$3),"⚙ OTIMIZAR","📊 COLETAR DADOS")))) -> 📊 COLETAR DADOS
A9: 4 | H9: =IF(D9=0,0,E9/D9) -> 0 | I9: =IF(E9=0,0,F9/E9) -> 0 | J9: =IF(G9=0,"—",F9/G9) -> — | K9: =G9*$E$3 -> 0 | L9: =IF(F9=0,"—",K9/F9) -> — | M9: =K9-F9 -> 0 | N9: =IF(E9>=$I$3,"✅ Sim","⏳ Falta "&$I$3-E9&" cliques") -> ⏳ Falta 100 cliques | O9: =IF(E9<$I$3,"📊 COLETAR DADOS",IF(AND(L9>=$C$3,E9>=$I$3),"✔ ESCALAR",IF(AND(F9>=$G$3,G9=0),"✖ PAUSAR / TROCAR OFERTA",IF(AND(L9>=1,L9<$C$3),"⚙ OTIMIZAR","📊 COLETAR DADOS")))) -> 📊 COLETAR DADOS
A10: 5 | H10: =IF(D10=0,0,E10/D10) -> 0 | I10: =IF(E10=0,0,F10/E10) -> 0 | J10: =IF(G10=0,"—",F10/G10) -> — | K10: =G10*$E$3 -> 0 | L10: =IF(F10=0,"—",K10/F10) -> — | M10: =K10-F10 -> 0 | N10: =IF(E10>=$I$3,"✅ Sim","⏳ Falta "&$I$3-E10&" cliques") -> ⏳ Falta 100 cliques | O10: =IF(E10<$I$3,"📊 COLETAR DADOS",IF(AND(L10>=$C$3,E10>=$I$3),"✔ ESCALAR",IF(AND(F10>=$G$3,G10=0),"✖ PAUSAR / TROCAR OFERTA",IF(AND(L10>=1,L10<$C$3),"⚙ OTIMIZAR","📊 COLETAR DADOS")))) -> 📊 COLETAR DADOS
A11: 6 | H11: =IF(D11=0,0,E11/D11) -> 0 | I11: =IF(E11=0,0,F11/E11) -> 0 | J11: =IF(G11=0,"—",F11/G11) -> — | K11: =G11*$E$3 -> 0 | L11: =IF(F11=0,"—",K11/F11) -> — | M11: =K11-F11 -> 0 | N11: =IF(E11>=$I$3,"✅ Sim","⏳ Falta "&$I$3-E11&" cliques") -> ⏳ Falta 100 cliques | O11: =IF(E11<$I$3,"📊 COLETAR DADOS",IF(AND(L11>=$C$3,E11>=$I$3),"✔ ESCALAR",IF(AND(F11>=$G$3,G11=0),"✖ PAUSAR / TROCAR OFERTA",IF(AND(L11>=1,L11<$C$3),"⚙ OTIMIZAR","📊 COLETAR DADOS")))) -> 📊 COLETAR DADOS
A12: 7 | H12: =IF(D12=0,0,E12/D12) -> 0 | I12: =IF(E12=0,0,F12/E12) -> 0 | J12: =IF(G12=0,"—",F12/G12) -> — | K12: =G12*$E$3 -> 0 | L12: =IF(F12=0,"—",K12/F12) -> — | M12: =K12-F12 -> 0 | N12: =IF(E12>=$I$3,"✅ Sim","⏳ Falta "&$I$3-E12&" cliques") -> ⏳ Falta 100 cliques | O12: =IF(E12<$I$3,"📊 COLETAR DADOS",IF(AND(L12>=$C$3,E12>=$I$3),"✔ ESCALAR",IF(AND(F12>=$G$3,G12=0),"✖ PAUSAR / TROCAR OFERTA",IF(AND(L12>=1,L12<$C$3),"⚙ OTIMIZAR","📊 COLETAR DADOS")))) -> 📊 COLETAR DADOS
A13: 8 | H13: =IF(D13=0,0,E13/D13) -> 0 | I13: =IF(E13=0,0,F13/E13) -> 0 | J13: =IF(G13=0,"—",F13/G13) -> — | K13: =G13*$E$3 -> 0 | L13: =IF(F13=0,"—",K13/F13) -> — | M13: =K13-F13 -> 0 | N13: =IF(E13>=$I$3,"✅ Sim","⏳ Falta "&$I$3-E13&" cliques") -> ⏳ Falta 100 cliques | O13: =IF(E13<$I$3,"📊 COLETAR DADOS",IF(AND(L13>=$C$3,E13>=$I$3),"✔ ESCALAR",IF(AND(F13>=$G$3,G13=0),"✖ PAUSAR / TROCAR OFERTA",IF(AND(L13>=1,L13<$C$3),"⚙ OTIMIZAR","📊 COLETAR DADOS")))) -> 📊 COLETAR DADOS

Sheet 💰 Resumo Financeiro
A1: 💰 RESUMO FINANCEIRO — DASHBOARD
A3: CONFIGURAÇÃO
A4: Comissão Conservadora | B4: 134
A5: Comissão Média Esperada | B5: 155
A6: Meta ROAS | B6: 2
A7: Budget Fase 1 | B7: 10
A8: Budget Fase 2 | B8: 50
A9: Budget Fase 3 | B9: 300
A12: ACUMULADO (dados da aba Controle Diário)
A13: Total Investido | B13: ='📊 Controle Diário'!F37 -> 0
A14: Total de Cliques | B14: ='📊 Controle Diário'!E37 -> 0
A15: Total de Conversões | B15: ='📊 Controle Diário'!G37 -> 0
A16: Receita Total | B16: ='📊 Controle Diário'!K37 -> 0
A17: Lucro Total | B17: ='📊 Controle Diário'!M37 -> 0
A18: ROAS Acumulado | B18: =IF(B13=0,0,B16/B13) -> 0
A19: CPA Acumulado | B19: =IF(B15=0,"—",B13/B15) -> —
A20: CTR Médio Geral | B20: ='📊 Controle Diário'!H37 -> 0
A23: PROJEÇÕES POR FASE
A24: Fase | B24: Investimento | C24: Cliques Esperados | D24: Conversões | E24: Receita Estimada | F24: Lucro Estimado
A25: Fase 1 — Validação | B25: $10 | C25: 12–20 | D25: 0–1 | E25: $0–$134 | F25: Meta: dados
A26: Fase 2 — Otimização | B26: $50 | C26: 60–100 | D26: 1 | E26: $134–$250 | F26: $84–$200
A27: Fase 3 — Escala | B27: $300/mês | C27: 375–600 | D27: 3–5 | E27: $400–$1.250 | F27: $100–$952
A30: ANÁLISE DE BREAKEVEN
A31: CPC Máximo Sustentável | B31: =B4*B33 -> 1.6 | C31: Comissão × Taxa de conversão esperada
A32: Taxa Conversão p/ Breakeven (CPC $0.80) | B32: =0.8/B4 -> 0.0059701493 | C32: CPC / Comissão = mínimo para não perder
A33: Taxa Conversão p/ ROAS 2.0 | B33: =(0.8*B6)/B4 -> 0.011940299 | C33: CPC × Meta ROAS / Comissão
A34: Taxa Conversão Esperada (estimativa) | B34: 0.01 | C34: Ajuste conforme dados reais (célula amarela)
A37: GRÁFICO: GASTO vs. RECEITA ACUMULADOS
A38: Métrica | B38: Valor Acumulado
A39: Gasto Total | B39: =B13 -> 0
A40: Receita Total | B40: =B16 -> 0
A41: Lucro Total | B41: =B17 -> 0
