Workbook

Sheet Instrucoes
A1: PLANILHA DE TRACKING — Afiliados (ClickBank · BuyGoods · MaxWeb · Google Ads · BR)
A3: Abas | B3: Para que serve
A4: Instrucoes | B4: Este guia
A5: Dashboard | B5: KPIs e resumo por rede e por canal Google (lê a aba Diario)
A6: Diario | B6: LANÇAMENTO DIÁRIO — 1 linha por dia/campanha. Principal aba de preenchimento
A7: Ofertas | B7: Cadastro de ofertas por rede (payout, terms, links, status)
A8: Campanhas_Google | B8: Cadastro de campanhas (naming, UTM, conversão, budget)
A9: Testes_KillScale | B9: Hipóteses de teste e decisão SCALE / OTIMIZAR / KILL
A10: MaxWeb_Postback | B10: Checklist de tracking MaxWeb + log de conversões
A11: BreakEven | B11: Calculadora de CPC máximo e alvo de escala
A14: Fluxo recomendado
A15: 1. Cadastre a oferta em Ofertas (rede, payout, geo, se Google permite, link).
A16: 2. Crie a campanha em Campanhas_Google com Campanha_ID padronizado e UTM igual ao ID.
A17: 3. Calcule break-even na aba BreakEven (comissão, refund, CVR esperada).
A18: 4. Se MaxWeb: complete MaxWeb_Postback antes de gastar.
A19: 5. Rode o teste e registre hipótese em Testes_KillScale.
A20: 6. Todo dia: preencha Diario (cliques, CPC, conversões, receita, refunds).
A21: 7. Use Dashboard para ver lucro por rede/canal e decida SCALE / OTIMIZAR / KILL.
A22: 8. Moeda: use a mesma moeda em Gasto e Receita (ou converta USD→BRL na Receita).
A24: Naming sugerido Campanha_ID
A25: [REDE]_[VERTICAL]_[GEO]_[CANAL]_[FUNIL]_vN | Ex: CB_WL_US_SEARCH_BRIDGE_v1 · MW_NUTRA_BR_YT_SL_v1
A27: Regra SCALE | B27: EPC >= 1.3 × CPC OU eCPA < payout líquido com margem — após volume mínimo de cliques
A28: Regra KILL | B28: Sem conversão com gasto >= orçamento de teste, ou EPC bem abaixo do CPC sem tendência
A29: Regra OTIMIZAR | B29: Perto do BE: trocar ângulo, negativas, bridge, criativo ou match de keyword

Sheet Dashboard
A1: TRACKING AFILIADOS — Dashboard
A2: Atualizado: 2026-07-15 | Redes: ClickBank · BuyGoods · MaxWeb · Hotmart/Eduzz/Monetizze · Google Ads
A4: Gasto Total (período) | B4: =SUMIF(Diario!A:A,">="&B12,Diario!L:L) -> 446.5 | C4: Receita / Comissões | D4: =SUMIF(Diario!A:A,">="&B12,Diario!N:N) -> 706 | E4: Lucro Líquido | F4: =D4-B4 -> 259.5
A6: ROAS | B6: =IF(B4=0,0,D4/B4) -> 1.581187 | C6: EPC Médio | D6: =IF(B8=0,0,D4/B8) -> 1.3074074 | E6: eCPA Médio | F6: =IF(D8=0,0,B4/D8) -> 21.261905
A8: Cliques | B8: =SUMIF(Diario!A:A,">="&B12,Diario!J:J) -> 540 | C8: Vendas / Leads | D8: =SUMIF(Diario!A:A,">="&B12,Diario!M:M) -> 21 | E8: CVR % | F8: =IF(B8=0,0,D8/B8) -> 0.038888889
A11: Filtro período (data início)
A12: Data início → | B12: 46204 | C12: (altere B12 para filtrar o dashboard)
A14: RESUMO POR REDE
A15: Rede | B15: Gasto | C15: Receita | D15: Lucro | E15: Cliques | F15: Conv. | G15: ROAS
A16: ClickBank | B16: =SUMIF(Diario!C:C,A16,Diario!L:L) -> 186 | C16: =SUMIF(Diario!C:C,A16,Diario!N:N) -> 180 | D16: =C16-B16 -> -6 | E16: =SUMIF(Diario!C:C,A16,Diario!J:J) -> 125 | F16: =SUMIF(Diario!C:C,A16,Diario!M:M) -> 3 | G16: =IF(B16=0,0,C16/B16) -> 0.96774194
A17: BuyGoods | B17: =SUMIF(Diario!C:C,A17,Diario!L:L) -> 112 | C17: =SUMIF(Diario!C:C,A17,Diario!N:N) -> 110 | D17: =C17-B17 -> -2 | E17: =SUMIF(Diario!C:C,A17,Diario!J:J) -> 140 | F17: =SUMIF(Diario!C:C,A17,Diario!M:M) -> 2 | G17: =IF(B17=0,0,C17/B17) -> 0.98214286
A18: MaxWeb | B18: =SUMIF(Diario!C:C,A18,Diario!L:L) -> 99 | C18: =SUMIF(Diario!C:C,A18,Diario!N:N) -> 96 | D18: =C18-B18 -> -3 | E18: =SUMIF(Diario!C:C,A18,Diario!J:J) -> 220 | F18: =SUMIF(Diario!C:C,A18,Diario!M:M) -> 12 | G18: =IF(B18=0,0,C18/B18) -> 0.96969697
A19: Hotmart | B19: =SUMIF(Diario!C:C,A19,Diario!L:L) -> 49.5 | C19: =SUMIF(Diario!C:C,A19,Diario!N:N) -> 320 | D19: =C19-B19 -> 270.5 | E19: =SUMIF(Diario!C:C,A19,Diario!J:J) -> 55 | F19: =SUMIF(Diario!C:C,A19,Diario!M:M) -> 4 | G19: =IF(B19=0,0,C19/B19) -> 6.4646465
A20: Eduzz | B20: =SUMIF(Diario!C:C,A20,Diario!L:L) -> 0 | C20: =SUMIF(Diario!C:C,A20,Diario!N:N) -> 0 | D20: =C20-B20 -> 0 | E20: =SUMIF(Diario!C:C,A20,Diario!J:J) -> 0 | F20: =SUMIF(Diario!C:C,A20,Diario!M:M) -> 0 | G20: =IF(B20=0,0,C20/B20) -> 0
A21: Monetizze | B21: =SUMIF(Diario!C:C,A21,Diario!L:L) -> 0 | C21: =SUMIF(Diario!C:C,A21,Diario!N:N) -> 0 | D21: =C21-B21 -> 0 | E21: =SUMIF(Diario!C:C,A21,Diario!J:J) -> 0 | F21: =SUMIF(Diario!C:C,A21,Diario!M:M) -> 0 | G21: =IF(B21=0,0,C21/B21) -> 0
A24: RESUMO POR CANAL GOOGLE ADS
A25: Canal Google | B25: Gasto | C25: Receita | D25: Lucro | E25: Cliques | F25: Conv. | G25: ROAS
A26: Search | B26: =SUMIF(Diario!G:G,A26,Diario!L:L) -> 235.5 | C26: =SUMIF(Diario!G:G,A26,Diario!N:N) -> 500 | D26: =C26-B26 -> 264.5 | E26: =SUMIF(Diario!G:G,A26,Diario!J:J) -> 180 | F26: =SUMIF(Diario!G:G,A26,Diario!M:M) -> 7 | G26: =IF(B26=0,0,C26/B26) -> 2.1231423
A27: YouTube | B27: =SUMIF(Diario!G:G,A27,Diario!L:L) -> 99 | C27: =SUMIF(Diario!G:G,A27,Diario!N:N) -> 96 | D27: =C27-B27 -> -3 | E27: =SUMIF(Diario!G:G,A27,Diario!J:J) -> 220 | F27: =SUMIF(Diario!G:G,A27,Diario!M:M) -> 12 | G27: =IF(B27=0,0,C27/B27) -> 0.96969697
A28: Demand Gen | B28: =SUMIF(Diario!G:G,A28,Diario!L:L) -> 112 | C28: =SUMIF(Diario!G:G,A28,Diario!N:N) -> 110 | D28: =C28-B28 -> -2 | E28: =SUMIF(Diario!G:G,A28,Diario!J:J) -> 140 | F28: =SUMIF(Diario!G:G,A28,Diario!M:M) -> 2 | G28: =IF(B28=0,0,C28/B28) -> 0.98214286
A29: PMax | B29: =SUMIF(Diario!G:G,A29,Diario!L:L) -> 0 | C29: =SUMIF(Diario!G:G,A29,Diario!N:N) -> 0 | D29: =C29-B29 -> 0 | E29: =SUMIF(Diario!G:G,A29,Diario!J:J) -> 0 | F29: =SUMIF(Diario!G:G,A29,Diario!M:M) -> 0 | G29: =IF(B29=0,0,C29/B29) -> 0
A30: Display | B30: =SUMIF(Diario!G:G,A30,Diario!L:L) -> 0 | C30: =SUMIF(Diario!G:G,A30,Diario!N:N) -> 0 | D30: =C30-B30 -> 0 | E30: =SUMIF(Diario!G:G,A30,Diario!J:J) -> 0 | F30: =SUMIF(Diario!G:G,A30,Diario!M:M) -> 0 | G30: =IF(B30=0,0,C30/B30) -> 0
A31: Outro | B31: =SUMIF(Diario!G:G,A31,Diario!L:L) -> 0 | C31: =SUMIF(Diario!G:G,A31,Diario!N:N) -> 0 | D31: =C31-B31 -> 0 | E31: =SUMIF(Diario!G:G,A31,Diario!J:J) -> 0 | F31: =SUMIF(Diario!G:G,A31,Diario!M:M) -> 0 | G31: =IF(B31=0,0,C31/B31) -> 0
A34: LEGENDA DECISÃO
A35: SCALE | B35: EPC >= 1.3x CPC (ou eCPA < payout com margem) + volume mínimo
A36: OTIMIZAR | B36: Perto do break-even; ajustar criativo/keyword/bridge
A37: KILL | B37: Abaixo do break-even sem tendência após teste mínimo
A39: Como usar: preencha a aba Diario (1 linha por dia/campanha). Ofertas e Campanhas_Google são cadastros. Testes registra kill/scale. MaxWeb_Postback valida tracking.

Sheet Diario
A1: Data | B1: Campanha_ID | C1: Rede | D1: Oferta | E1: Vertical | F1: Geo | G1: Canal_Google | H1: Funil | I1: Impressoes | J1: Cliques | K1: CPC | L1: Gasto | M1: Conversoes | N1: Receita_Comissao | O1: Refunds_Clawback | P1: Receita_Liquida | Q1: Lucro | R1: EPC | S1: CVR | T1: ROAS | U1: eCPA | V1: Decisao | W1: Notas
A2: 46213 | B2: CB_WL_US_SEARCH_BRIDGE_v1 | C2: ClickBank | D2: Offer Alpha WL | E2: Weight Loss | F2: US | G2: Search | H2: Bridge | I2: 1200 | J2: 85 | K2: 1.2 | L2: =J2*K2 -> 102 | M2: 3 | N2: 180 | O2: 0 | P2: =N2-O2 -> 180 | Q2: =P2-L2 -> 78 | R2: =IF(J2=0,0,P2/J2) -> 2.1176471 | S2: =IF(J2=0,0,M2/J2) -> 0.035294118 | T2: =IF(L2=0,0,P2/L2) -> 1.7647059 | U2: =IF(M2=0,0,L2/M2) -> 34 | V2: SCALE | W2: Bom QS
A3: 46214 | B3: MW_NUTRA_BR_YT_SL_v1 | C3: MaxWeb | D3: Smartlink Nutra | E3: Nutra | F3: BR | G3: YouTube | H3: Smartlink | I3: 8000 | J3: 220 | K3: 0.45 | L3: =J3*K3 -> 99 | M3: 12 | N3: 96 | O3: 1 | P3: =N3-O3 -> 95 | Q3: =P3-L3 -> -4 | R3: =IF(J3=0,0,P3/J3) -> 0.43181818 | S3: =IF(J3=0,0,M3/J3) -> 0.054545455 | T3: =IF(L3=0,0,P3/L3) -> 0.95959596 | U3: =IF(M3=0,0,L3/M3) -> 8.25 | V3: OTIMIZAR | W3: Testar hook 2
A4: 46215 | B4: BG_BEAUTY_US_DGEN_v1 | C4: BuyGoods | D4: Serum X | E4: Beauty | F4: US | G4: Demand Gen | H4: Bridge | I4: 3500 | J4: 140 | K4: 0.8 | L4: =J4*K4 -> 112 | M4: 2 | N4: 110 | O4: 0 | P4: =N4-O4 -> 110 | Q4: =P4-L4 -> -2 | R4: =IF(J4=0,0,P4/J4) -> 0.78571429 | S4: =IF(J4=0,0,M4/J4) -> 0.014285714 | T4: =IF(L4=0,0,P4/L4) -> 0.98214286 | U4: =IF(M4=0,0,L4/M4) -> 56 | V4: OTIMIZAR | W4: CVR baixa
A5: 46216 | B5: CB_MM_US_SEARCH_v2 | C5: ClickBank | D5: Offer Beta MMO | E5: Make Money | F5: US | G5: Search | H5: Bridge | I5: 900 | J5: 40 | K5: 2.1 | L5: =J5*K5 -> 84 | M5: 0 | N5: 0 | O5: 0 | P5: =N5-O5 -> 0 | Q5: =P5-L5 -> -84 | R5: =IF(J5=0,0,P5/J5) -> 0 | S5: =IF(J5=0,0,M5/J5) -> 0 | T5: =IF(L5=0,0,P5/L5) -> 0 | U5: =IF(M5=0,0,L5/M5) -> 0 | V5: KILL | W5: CPC alto zero sale
A6: 46217 | B6: HT_CURSO_BR_SEARCH_v1 | C6: Hotmart | D6: Curso Y | E6: Educacao | F6: BR | G6: Search | H6: Direct | I6: 600 | J6: 55 | K6: 0.9 | L6: =J6*K6 -> 49.5 | M6: 4 | N6: 320 | O6: 0 | P6: =N6-O6 -> 320 | Q6: =P6-L6 -> 270.5 | R6: =IF(J6=0,0,P6/J6) -> 5.8181818 | S6: =IF(J6=0,0,M6/J6) -> 0.072727273 | T6: =IF(L6=0,0,P6/L6) -> 6.4646465 | U6: =IF(M6=0,0,L6/M6) -> 12.375 | V6: SCALE | W6: Lançamento D2
L7: =IF(J7="","",J7*K7) | P7: =IF(N7="","",N7-IF(O7="",0,O7)) | Q7: =IF(P7="","",P7-IF(L7="",0,L7)) | R7: =IF(OR(J7="",J7=0),"",P7/J7) | S7: =IF(OR(J7="",J7=0),"",M7/J7) | T7: =IF(OR(L7="",L7=0),"",P7/L7) | U7: =IF(OR(M7="",M7=0),"",L7/M7)
L8: =IF(J8="","",J8*K8) | P8: =IF(N8="","",N8-IF(O8="",0,O8)) | Q8: =IF(P8="","",P8-IF(L8="",0,L8)) | R8: =IF(OR(J8="",J8=0),"",P8/J8) | S8: =IF(OR(J8="",J8=0),"",M8/J8) | T8: =IF(OR(L8="",L8=0),"",P8/L8) | U8: =IF(OR(M8="",M8=0),"",L8/M8)
L9: =IF(J9="","",J9*K9) | P9: =IF(N9="","",N9-IF(O9="",0,O9)) | Q9: =IF(P9="","",P9-IF(L9="",0,L9)) | R9: =IF(OR(J9="",J9=0),"",P9/J9) | S9: =IF(OR(J9="",J9=0),"",M9/J9) | T9: =IF(OR(L9="",L9=0),"",P9/L9) | U9: =IF(OR(M9="",M9=0),"",L9/M9)
L10: =IF(J10="","",J10*K10) | P10: =IF(N10="","",N10-IF(O10="",0,O10)) | Q10: =IF(P10="","",P10-IF(L10="",0,L10)) | R10: =IF(OR(J10="",J10=0),"",P10/J10) | S10: =IF(OR(J10="",J10=0),"",M10/J10) | T10: =IF(OR(L10="",L10=0),"",P10/L10) | U10: =IF(OR(M10="",M10=0),"",L10/M10)
L11: =IF(J11="","",J11*K11) | P11: =IF(N11="","",N11-IF(O11="",0,O11)) | Q11: =IF(P11="","",P11-IF(L11="",0,L11)) | R11: =IF(OR(J11="",J11=0),"",P11/J11) | S11: =IF(OR(J11="",J11=0),"",M11/J11) | T11: =IF(OR(L11="",L11=0),"",P11/L11) | U11: =IF(OR(M11="",M11=0),"",L11/M11)
L12: =IF(J12="","",J12*K12) | P12: =IF(N12="","",N12-IF(O12="",0,O12)) | Q12: =IF(P12="","",P12-IF(L12="",0,L12)) | R12: =IF(OR(J12="",J12=0),"",P12/J12) | S12: =IF(OR(J12="",J12=0),"",M12/J12) | T12: =IF(OR(L12="",L12=0),"",P12/L12) | U12: =IF(OR(M12="",M12=0),"",L12/M12)
L13: =IF(J13="","",J13*K13) | P13: =IF(N13="","",N13-IF(O13="",0,O13)) | Q13: =IF(P13="","",P13-IF(L13="",0,L13)) | R13: =IF(OR(J13="",J13=0),"",P13/J13) | S13: =IF(OR(J13="",J13=0),"",M13/J13) | T13: =IF(OR(L13="",L13=0),"",P13/L13) | U13: =IF(OR(M13="",M13=0),"",L13/M13)
L14: =IF(J14="","",J14*K14) | P14: =IF(N14="","",N14-IF(O14="",0,O14)) | Q14: =IF(P14="","",P14-IF(L14="",0,L14)) | R14: =IF(OR(J14="",J14=0),"",P14/J14) | S14: =IF(OR(J14="",J14=0),"",M14/J14) | T14: =IF(OR(L14="",L14=0),"",P14/L14) | U14: =IF(OR(M14="",M14=0),"",L14/M14)
L15: =IF(J15="","",J15*K15) | P15: =IF(N15="","",N15-IF(O15="",0,O15)) | Q15: =IF(P15="","",P15-IF(L15="",0,L15)) | R15: =IF(OR(J15="",J15=0),"",P15/J15) | S15: =IF(OR(J15="",J15=0),"",M15/J15) | T15: =IF(OR(L15="",L15=0),"",P15/L15) | U15: =IF(OR(M15="",M15=0),"",L15/M15)
L16: =IF(J16="","",J16*K16) | P16: =IF(N16="","",N16-IF(O16="",0,O16)) | Q16: =IF(P16="","",P16-IF(L16="",0,L16)) | R16: =IF(OR(J16="",J16=0),"",P16/J16) | S16: =IF(OR(J16="",J16=0),"",M16/J16) | T16: =IF(OR(L16="",L16=0),"",P16/L16) | U16: =IF(OR(M16="",M16=0),"",L16/M16)
L17: =IF(J17="","",J17*K17) | P17: =IF(N17="","",N17-IF(O17="",0,O17)) | Q17: =IF(P17="","",P17-IF(L17="",0,L17)) | R17: =IF(OR(J17="",J17=0),"",P17/J17) | S17: =IF(OR(J17="",J17=0),"",M17/J17) | T17: =IF(OR(L17="",L17=0),"",P17/L17) | U17: =IF(OR(M17="",M17=0),"",L17/M17)
L18: =IF(J18="","",J18*K18) | P18: =IF(N18="","",N18-IF(O18="",0,O18)) | Q18: =IF(P18="","",P18-IF(L18="",0,L18)) | R18: =IF(OR(J18="",J18=0),"",P18/J18) | S18: =IF(OR(J18="",J18=0),"",M18/J18) | T18: =IF(OR(L18="",L18=0),"",P18/L18) | U18: =IF(OR(M18="",M18=0),"",L18/M18)
... L50: =IF(J50="","",J50*K50) | P50: =IF(N50="","",N50-IF(O50="",0,O50)) | Q50: =IF(P50="","",P50-IF(L50="",0,L50)) | R50: =IF(OR(J50="",J50=0),"",P50/J50) | S50: =IF(OR(J50="",J50=0),"",M50/J50) | T50: =IF(OR(L50="",L50=0),"",P50/L50) | U50: =IF(OR(M50="",M50=0),"",L50/M50)
A52: Valores Rede: ClickBank | BuyGoods | MaxWeb | Hotmart | Eduzz | Monetizze
A53: Canal_Google: Search | YouTube | Demand Gen | PMax | Display | Outro
A54: Funil: Direct | Bridge | Smartlink | Review | Lancamento
A55: Decisao: SCALE | OTIMIZAR | KILL | TESTE
A56: Preencha: Data, Campanha_ID, Rede, Oferta, Vertical, Geo, Canal, Funil, Impressoes, Cliques, CPC, Conversoes, Receita, Refunds, Decisao, Notas. O resto calcula sozinho.

Sheet Ofertas
A1: Oferta_ID | B1: Rede | C1: Nome_Oferta | D1: Vertical | E1: Geo_Permitidos | F1: Payout_Comissao | G1: Modelo | H1: Gravity_EPC_Ref | I1: Upsells | J1: Trademark_Bidding | K1: Google_Permitido | L1: Funil_Recomendado | M1: Vendor_Terms_OK | N1: Link_Hop_Smartlink | O1: BreakEven_CPC | P1: Status | Q1: Data_Inicio_Teste | R1: Resultado | S1: Notas
A2: CB-001 | B2: ClickBank | C2: Offer Alpha WL | D2: Weight Loss | E2: US,CA,AU | F2: US$60 avg | G2: CPA % + upsell | H2: Gravity 80 / EPC $1.2 | I2: Sim | J2: Proibido | K2: Search,YT com bridge | L2: Bridge | M2: Sim | N2: https://hop.link/exemplo | O2: 1.5 | P2: Ativa | Q2: 46204 | R2: SCALE | S2: Melhor EPC Search
A3: BG-001 | B3: BuyGoods | C3: Serum X | D3: Beauty | E3: US,UK | F3: US$55 | G3: CPA | H3: — | I3: Sim | J3: Proibido | K3: Demand Gen,YT | L3: Bridge | M3: Sim | N3: https://buygoods.exemplo | O3: 1.1 | P3: Teste | Q3: 46213 | R3: OTIMIZAR | S3: Precisa criativo UGC
A4: MW-001 | B4: MaxWeb | C4: Smartlink Nutra BR | D4: Nutra | E4: BR | F4: R$8 CPL | G4: CPL | H4: — | I4: N/A | J4: N/A | K4: YT,Search | L4: Smartlink | M4: Sim | N4: https://maxweb.exemplo/sl | O4: 0.6 | P4: Ativa | Q4: 46208 | R4: OTIMIZAR | S4: Postback OK
A5: HT-001 | B5: Hotmart | C5: Curso Y | D5: Educacao | E5: BR | F5: R$80 (50%) | G5: % comissao | H5: — | I5: Bump | J5: Ver produtor | K5: Search | L5: Direct/Lancamento | M5: Sim | N5: https://hotmart.exemplo | O5: 2 | P5: Ativa | Q5: 46215 | R5: SCALE | S5: Carrinho aberto

Sheet Campanhas_Google
A1: Campanha_ID | B1: Nome_Google | C1: Tipo | D1: Rede_Afiliado | E1: Oferta_ID | F1: Geo | G1: Orcamento_Dia | H1: Estrategia_Lance | I1: Conversao_Config | J1: Valor_Conv_Estimado | K1: UTM_Campaign | L1: URL_Final_Bridge | M1: Status | N1: QS_Notas | O1: Negativas_OK | P1: Data_Criacao | Q1: Notas
A2: CB_WL_US_SEARCH_BRIDGE_v1 | B2: CB | WL | US | Search | Bridge | C2: Search | D2: ClickBank | E2: CB-001 | F2: US | G2: 50 | H2: Maximizar conversões | I2: Compra (valor comissão) | J2: 60 | K2: cb_wl_us_search_v1 | L2: https://seusite.com/review-alpha | M2: Ativa | N2: QS 7+ | O2: Sim | P2: 46211 | Q2: Exact + phrase
A3: MW_NUTRA_BR_YT_SL_v1 | B3: MW | Nutra | BR | YT | SL | C3: YouTube | D3: MaxWeb | E3: MW-001 | F3: BR | G3: 40 | H3: CPV / Max conv | I3: Lead postback | J3: 8 | K3: mw_nutra_br_yt_v1 | L3: https://smartlink.maxweb/xxx | M3: Ativa | N3: — | O3: Sim | P3: 46212 | Q3: 3 criativos
A4: BG_BEAUTY_US_DGEN_v1 | B4: BG | Beauty | US | DGen | C4: Demand Gen | D4: BuyGoods | E4: BG-001 | F4: US | G4: 30 | H4: Max conversões | I4: Compra | J4: 55 | K4: bg_beauty_us_dgen_v1 | L4: https://seusite.com/serum-x | M4: Pausada | N4: — | O4: Sim | P4: 46214 | Q4: Aguardando UGC

Sheet Testes_KillScale
A1: Teste_ID | B1: Data_Inicio | C1: Data_Fim | D1: Campanha_ID | E1: Rede | F1: Oferta | G1: Hipotese_Angulo | H1: Orcamento_Teste | I1: Cliques_Minimos | J1: Gasto_Real | K1: Conv | L1: Receita | M1: EPC | N1: CPC_Medio | O1: BreakEven_CPC | P1: Resultado | Q1: Proximo_Passo | R1: Aprendizado
A2: T-001 | B2: 46213 | C2: 46215 | D2: CB_WL_US_SEARCH_BRIDGE_v1 | E2: ClickBank | F2: Offer Alpha WL | G2: Dor: 'não consigo emagrecer depois dos 40' | H2: 80 | I2: 80 | J2: 102 | K2: 3 | L2: 180 | M2: =IF(J2=0,"",L2*N2/J2) -> 2.1176471 | N2: 1.2 | O2: 1.5 | P2: SCALE | Q2: Subir budget 25% | R2: Hook idade converte
A3: T-002 | B3: 46214 | C3: 46216 | D3: CB_MM_US_SEARCH_v2 | E3: ClickBank | F3: Offer Beta MMO | G3: Promessa renda extra home office | H3: 60 | I3: 50 | J3: 84 | K3: 0 | L3: 0 | M3: =IF(J3=0,"",L3*N3/J3) -> 0 | N3: 2.1 | O3: 1.8 | P3: KILL | Q3: Pausar oferta | R3: CPC Search MMO inviável neste geo
A4: T-003 | B4: 46214 | C4: 46217 | D4: MW_NUTRA_BR_YT_SL_v1 | E4: MaxWeb | F4: Smartlink Nutra | G4: UGC depoimento 15s | H4: 50 | I4: 150 | J4: 99 | K4: 12 | L4: 96 | M4: =IF(J4=0,"",L4*N4/J4) -> 0.43636364 | N4: 0.45 | O4: 0.6 | P4: OTIMIZAR | Q4: Trocar 2 criativos | R4: eCPA perto do payout
M5: =IF(OR(J5="",J5=0,N5=""),"",L5*N5/J5)
M6: =IF(OR(J6="",J6=0,N6=""),"",L6*N6/J6)
M7: =IF(OR(J7="",J7=0,N7=""),"",L7*N7/J7)
M8: =IF(OR(J8="",J8=0,N8=""),"",L8*N8/J8)
M9: =IF(OR(J9="",J9=0,N9=""),"",L9*N9/J9)
M10: =IF(OR(J10="",J10=0,N10=""),"",L10*N10/J10)
M11: =IF(OR(J11="",J11=0,N11=""),"",L11*N11/J11)
M12: =IF(OR(J12="",J12=0,N12=""),"",L12*N12/J12)
M13: =IF(OR(J13="",J13=0,N13=""),"",L13*N13/J13)
M14: =IF(OR(J14="",J14=0,N14=""),"",L14*N14/J14)
M15: =IF(OR(J15="",J15=0,N15=""),"",L15*N15/J15)
M16: =IF(OR(J16="",J16=0,N16=""),"",L16*N16/J16)
... M24: =IF(OR(J24="",J24=0,N24=""),"",L24*N24/J24)
A26: Regra prática: SCALE se EPC >= 1.3 × CPC (ou eCPA < payout com margem) após cliques mínimos. KILL se sem conversão e gasto >= orçamento teste. OTIMIZAR se no meio.

Sheet MaxWeb_Postback
A1: MAXWEB — Checklist de Tracking / Postback
A3: Item | B3: Status | C3: Valor / URL / Nota | D3: OK?
A4: Conta MaxWeb ativa | B4: Pendente | C4: login / manager
A5: Offer ou Smartlink escolhido | B5: Pendente | C5: ID da offer
A6: Tracking template / token clickid | B6: Pendente | C6: ex: {clickid} ou subid
A7: URL de postback configurada | B7: Pendente | C7: https://sua-rede-ou-tracker/...
A8: Parametros payout / event | B8: Pendente | C8: lead, sale, revshare
A9: Teste de conversão manual | B9: Pendente | C9: 1 lead/sale teste
A10: Match rate Google vs MaxWeb | B10: Pendente | C10: meta > 85%
A11: Pixel Google Ads / GTM | B11: Pendente | C11: conversion action
A12: UTMs padronizados | B12: Pendente | C12: utm_campaign = Campanha_ID
A13: Held / Rejected monitorado | B13: Pendente | C13: revisar 1x/semana
A14: eCPA vs Payout documentado | B14: Pendente | C14: aba Diario
A15: Geo e device alinhados à offer | B15: Pendente | C15: sem tráfego inválido
A17: LOG DE CONVERSÕES (cole do painel ou tracker)
A18: Data_Hora | B18: ClickID | C18: Offer | D18: Evento | E18: Payout | F18: Status | G18: Campanha_Google | H18: Obs
A41: Fórmula mental: Lucro MaxWeb ≈ Soma(Payout aprovado) − Gasto Google − Clawbacks. Não escale com held alto.

Sheet BreakEven
A1: quero crieaEu quero criar um grande repositório aí, um checklist para que eu nunca erre nas campanhas de ads do Clickbank nos Estados Unidos. Eu quero o checklist de tudo que eu tenho que fazer para fazer tudo certo sem tomar strike na conta de afiliado. Criando a página de pré-venda do modo mais otimizado e mais perfeito possível. Utilizando as ferramentas de AI que possam ser úteis ou gratuitas ou até APIs de AI que eu possa criar para criar esse fluxo e os loops necessários. Para eu poder executar esse checklist para uma campanha que eu já tenho aprovada. Onde eu agora estou na fase de criar para a página pré-venda já tenho todo o link do afiliado. Agora eu preciso ir para esse caminho.
A3: Entradas
A4: Comissão média por venda/lead | B4: 60 | C4: ← edite
A5: Refund / clawback estimado | B5: 0.1 | C5: ← edite
A6: CVR (click → conversão) | B6: 0.02 | C6: ← edite
A7: Fator margem (1.3 = SCALE threshold) | B7: 1.3 | C7: ← edite
A9: Resultados
A10: Comissão líquida (após refund) | B10: =B4*(1-B5) -> 54
A11: EPC break-even (comissao_liq × CVR) | B11: =B10*B6 -> 1.08
A12: CPC máximo break-even | B12: =B11 -> 1.08 | C12: CPC deve ser < este valor para não perder
A13: CPC alvo para SCALE (BE / margem) | B13: =B12/B7 -> 0.83076923 | C13: Meta prática de CPC para escalar
A14: eCPA máximo (≈ comissão líquida) | B14: =B10 -> 54 | C14: Para MaxWeb CPL/CPA: eCPA < payout líquido
A16: Exemplo rápido
A17: Se comissão R$60, refund 10%, CVR 2% → comissão líq R$54 → EPC BE R$1,08 → CPC SCALE alvo ≈ R$0,83 com margem 1.3
A19: Tabela de sensibilidade CVR × CPC máx (comissão e refund das células B4/B5)
A20: CVR | B20: CPC máx BE | C20: CPC alvo SCALE
A21: 0.005 | B21: =$B$10*A21 -> 0.27 | C21: =B21/$B$7 -> 0.20769231
A22: 0.01 | B22: =$B$10*A22 -> 0.54 | C22: =B22/$B$7 -> 0.41538462
A23: 0.015 | B23: =$B$10*A23 -> 0.81 | C23: =B23/$B$7 -> 0.62307692
A24: 0.02 | B24: =$B$10*A24 -> 1.08 | C24: =B24/$B$7 -> 0.83076923
A25: 0.025 | B25: =$B$10*A25 -> 1.35 | C25: =B25/$B$7 -> 1.0384615
A26: 0.03 | B26: =$B$10*A26 -> 1.62 | C26: =B26/$B$7 -> 1.2461538
A27: 0.04 | B27: =$B$10*A27 -> 2.16 | C27: =B27/$B$7 -> 1.6615385
A28: 0.05 | B28: =$B$10*A28 -> 2.7 | C28: =B28/$B$7 -> 2.0769231
